chrysalis/__init__.py
chrysalis/ch_errors.py
chrysalis/chrysalis.py
chrysalis/chunker.py
chrysalis/hls.py
chrysalis/live_video_image.py
chrysalis/log.py
chrysalis/models.py
chrysalis/past_video_image.py
chrysalis/probe.py
chrysalis/video_history.py
tests/__init__.py
tests/test_chrysalis.py
chrysalis-1.0.0.dist-info/LICENSE
chrysalis-1.0.0.dist-info/METADATA
chrysalis-1.0.0.dist-info/WHEEL
chrysalis-1.0.0.dist-info/top_level.txt
chrysalis-1.0.0.dist-info/RECORD
