Metadata-Version: 2.1
Name: chrysalis
Version: 1.0.0
Summary: Chrysalis Python Cloud SDK for streaming live media
Home-page: https://github.com/chryscloud/chrys-cloud-sdk-python.git
Author: Igor Rendulic
License: UNKNOWN
Platform: UNKNOWN
Classifier: Development Status :: 4 - Beta
Classifier: Intended Audience :: Developers
Classifier: Programming Language :: Python :: 3
Classifier: License :: OSI Approved :: Apache Software License
Classifier: Operating System :: OS Independent
Classifier: Topic :: Software Development :: Libraries :: Python Modules
Classifier: Topic :: Multimedia :: Sound/Audio
Classifier: Topic :: Multimedia :: Sound/Audio :: Conversion
Classifier: Topic :: Multimedia :: Video
Classifier: Topic :: Multimedia :: Video :: Conversion
Requires-Python: >=3.6
Requires-Dist: redis
Requires-Dist: av
Requires-Dist: numpy
